despike/__init__.py
despike/box.py
despike/despike.py
despike/mean.py
despike/median.py
despike-0.1.0.dist-info/METADATA
despike-0.1.0.dist-info/RECORD
despike-0.1.0.dist-info/WHEEL
despike-0.1.0.dist-info/pbr.json
despike-0.1.0.dist-info/top_level.txt
