Metadata-Version: 2.1
Name: despike
Version: 0.1.0
Summary: Python package to remove spike in 2D images
Home-page: http://github.com/seignovert/despike
Author: Benoit Seignovert
Author-email: despike@seignovert.fr
License: MIT
Keywords: despiking,spike,image processing
Platform: UNKNOWN
Classifier: Development Status :: 4 - Beta
Classifier: Intended Audience :: Science/Research
Classifier: Natural Language :: English
Classifier: License :: OSI Approved :: MIT License
Classifier: Programming Language :: Python
Classifier: Programming Language :: Python :: 2.7
Classifier: Programming Language :: Python :: 3.6
Classifier: Topic :: Scientific/Engineering
Classifier: Topic :: Scientific/Engineering :: Image Recognition
Classifier: Topic :: Scientific/Engineering :: Information Analysis
Classifier: Topic :: Scientific/Engineering :: Visualization
Requires-Dist: numpy
